jease/__init__.py
jease/core.py
jease-0.1.0.dist-info/licenses/LICENSE
jease-0.1.0.dist-info/METADATA
jease-0.1.0.dist-info/WHEEL
jease-0.1.0.dist-info/top_level.txt
jease-0.1.0.dist-info/RECORD
