Metadata-Version: 2.4
Name: jease
Version: 0.1.0
Summary: JEase - JSON made easy: chainable, safe, and beginner-friendly JSON manipulation in Python
Home-page: https://github.com/VaibhavRawat27/jease
Author: Vaibhav Rawat
Author-email: rawatvaibhav27@gmail.com
License: MIT
Classifier: Programming Language :: Python :: 3
Classifier: License :: OSI Approved :: MIT License
Classifier: Operating System :: OS Independent
Requires-Python: >=3.8
License-File: LICENSE
Dynamic: author
Dynamic: author-email
Dynamic: classifier
Dynamic: description
Dynamic: description-content-type
Dynamic: home-page
Dynamic: license
Dynamic: license-file
Dynamic: requires-python
Dynamic: summary
